notion_lab/__init__.py
notion_lab/converter/Converter.py
notion_lab/converter/HtmlCvt.py
notion_lab/converter/MDCvt.py
notion_lab/converter/__init__.py
notion_lab/converter/util/__init__.py
notion_lab/converter/util/html/__init__.py
notion_lab/converter/util/html/html.py
notion_lab/converter/util/html/elements/Code.py
notion_lab/converter/util/html/elements/Image.py
notion_lab/converter/util/html/elements/List.py
notion_lab/converter/util/html/elements/TableRow.py
notion_lab/converter/util/html/elements/Text.py
notion_lab/converter/util/html/elements/Toggle.py
notion_lab/converter/util/html/elements/__init__.py
notion_lab/converter/util/md/__init__.py
notion_lab/converter/util/md/md.py
notion_lab/database/DB.py
notion_lab/database/__init__.py
NotionLab-1.1.4.dist-info/LICENSE
NotionLab-1.1.4.dist-info/METADATA
NotionLab-1.1.4.dist-info/WHEEL
NotionLab-1.1.4.dist-info/top_level.txt
NotionLab-1.1.4.dist-info/RECORD
