Metadata-Version: 2.1
Name: NotionLab
Version: 1.1.4
Summary: A kit for Notion based on Notion Python SDK.
Home-page: https://github.com/ElaBosak233/NotionLab
Author: ElaBosak233
Author-email: ElaBosak233@gmail.com
License: MIT Licence
Keywords: notion,kit,parser,html,markdown,lab
Platform: any
License-File: LICENSE
Requires-Dist: notion-client
